pyswitchbot-1.0.0.dist-info/licenses/LICENSE
switchbot/__init__.py
switchbot/adv_parser.py
switchbot/api_config.py
switchbot/discovery.py
switchbot/enum.py
switchbot/helpers.py
switchbot/models.py
switchbot/utils.py
switchbot/adv_parsers/__init__.py
switchbot/adv_parsers/air_purifier.py
switchbot/adv_parsers/art_frame.py
switchbot/adv_parsers/blind_tilt.py
switchbot/adv_parsers/bot.py
switchbot/adv_parsers/bulb.py
switchbot/adv_parsers/ceiling_light.py
switchbot/adv_parsers/climate_panel.py
switchbot/adv_parsers/contact.py
switchbot/adv_parsers/curtain.py
switchbot/adv_parsers/fan.py
switchbot/adv_parsers/hub2.py
switchbot/adv_parsers/hub3.py
switchbot/adv_parsers/hubmini_matter.py
switchbot/adv_parsers/humidifier.py
switchbot/adv_parsers/keypad.py
switchbot/adv_parsers/keypad_vision.py
switchbot/adv_parsers/leak.py
switchbot/adv_parsers/light_strip.py
switchbot/adv_parsers/lock.py
switchbot/adv_parsers/meter.py
switchbot/adv_parsers/motion.py
switchbot/adv_parsers/plug.py
switchbot/adv_parsers/presence_sensor.py
switchbot/adv_parsers/relay_switch.py
switchbot/adv_parsers/remote.py
switchbot/adv_parsers/roller_shade.py
switchbot/adv_parsers/smart_thermostat_radiator.py
switchbot/adv_parsers/vacuum.py
switchbot/const/__init__.py
switchbot/const/air_purifier.py
switchbot/const/climate.py
switchbot/const/evaporative_humidifier.py
switchbot/const/fan.py
switchbot/const/hub2.py
switchbot/const/hub3.py
switchbot/const/light.py
switchbot/const/lock.py
switchbot/const/presence_sensor.py
switchbot/devices/__init__.py
switchbot/devices/air_purifier.py
switchbot/devices/art_frame.py
switchbot/devices/base_cover.py
switchbot/devices/base_light.py
switchbot/devices/blind_tilt.py
switchbot/devices/bot.py
switchbot/devices/bulb.py
switchbot/devices/ceiling_light.py
switchbot/devices/contact.py
switchbot/devices/curtain.py
switchbot/devices/device.py
switchbot/devices/evaporative_humidifier.py
switchbot/devices/fan.py
switchbot/devices/humidifier.py
switchbot/devices/keypad.py
switchbot/devices/keypad_vision.py
pyswitchbot-1.0.0.dist-info/METADATA
pyswitchbot-1.0.0.dist-info/WHEEL
pyswitchbot-1.0.0.dist-info/top_level.txt
pyswitchbot-1.0.0.dist-info/RECORD
