Metadata-Version: 2.4
Name: PySwitchbot
Version: 1.0.0
Summary: A library to communicate with Switchbot
Home-page: https://github.com/sblibs/pySwitchbot/
Author: Daniel Hjelseth Hoyer
License: MIT
Classifier: Development Status :: 3 - Alpha
Classifier: Environment :: Other Environment
Classifier: Intended Audience :: Developers
Classifier: Operating System :: OS Independent
Classifier: Programming Language :: Python
Classifier: Topic :: Home Automation
Classifier: Topic :: Software Development :: Libraries :: Python Modules
Requires-Python: >=3.11
License-File: LICENSE
Requires-Dist: aiohttp>=3.9.5
Requires-Dist: bleak>=0.19.0
Requires-Dist: bleak-retry-connector>=3.4.0
Requires-Dist: cryptography>=39.0.0
Requires-Dist: pyOpenSSL>=23.0.0
Dynamic: author
Dynamic: classifier
Dynamic: description
Dynamic: description-content-type
Dynamic: home-page
Dynamic: license
Dynamic: license-file
Dynamic: requires-dist
Dynamic: requires-python
Dynamic: summary
